toolagent/__init__.py
toolagent/pipeline.py
toolagent/agents/__init__.py
toolagent/data/__init__.py
toolagent/model/__init__.py
toolagent/model/llm/__init__.py
toolagent/prompt/__init__.py
toolagent/retrieval/__init__.py
toolagent/retrieval/retriever.py
toolagent/retrieval/embedding/__init__.py
toolagent/retrieval/vectorstore/__init__.py
toolagent/tools/__init__.py
toolagent/types/__init__.py
toolagent/utils/__init__.py
toolagent/utils/_log.py
toolagent/utils/file_io.py
toolagent/utils/random.py
toolagent-0.0.0.dist-info/LICENSE
toolagent-0.0.0.dist-info/METADATA
toolagent-0.0.0.dist-info/WHEEL
toolagent-0.0.0.dist-info/top_level.txt
toolagent-0.0.0.dist-info/RECORD
