Metadata-Version: 2.1
Name: toolagent
Version: 0.0.0
Summary: A Highly-Modularized Tool Learning Framework for LLM Based Agent
Author-email: Mengsong Wu <radi.cat@qq.com>, Tong Zhu <tzhu1997@outlook.com>, Xiang Zhang <1805565641@qq.com>, Han Han <1411839206@qq.com>
Maintainer-email: Mengsong Wu <radi.cat@qq.com>, Tong Zhu <tzhu1997@outlook.com>, Xiang Zhang <1805565641@qq.com>, Han Han <1411839206@qq.com>
License: Apache License
Project-URL: Homepage, https://github.com/NoobNLP/ToolAgent
Project-URL: Bug Tracker, https://github.com/NoobNLP/ToolAgent/issues
Project-URL: Source, https://github.com/NoobNLP/ToolAgent/
Requires-Python: >=3.10
License-File: LICENSE
Requires-Dist: torch
Requires-Dist: transformers
Requires-Dist: openai
